{
    "name": "Worms Bind",
    "type": "item",
    "img": "modules/omini-system-assets/assets/icons/skills/enemies/specters/terrestrial/raimi/worms_bind.webp",
    "system": {
        "props": {
            "itemType": "skill",
            "skillType": "Action",
            "rarity": "rare",
            "tier": 6,
            "source": "Raimi (Specter)",
            "icCost": 5,
            "damage": "Bind",
            "actionMacro": "worms_bind_action",
            "description": "<p><strong>[Worms Bind]</strong></p><p>Tentáculos subterrâneos.</p><p><strong>Custo:</strong> 5 IC</p><p><strong>Tipo:</strong> Action</p>"
        }
    }
}
