{
    "name": "Dead End Symphony",
    "type": "item",
    "img": "modules/omini-system-assets/assets/icons/skills/enemies/marinas/general/sorrento/dead_end_symphony.webp",
    "system": {
        "props": {
            "itemType": "skill",
            "skillType": "Field",
            "rarity": "mythic",
            "tier": 10,
            "source": "Sorrento (Marina)",
            "icCost": 15,
            "damage": "-Cosmo Limit",
            "actionMacro": "dead_end_symphony_action",
            "description": "<p><strong>[Dead End Symphony]</strong></p><p>Sinfonia Final. Reduz limite de Cosmo.</p><p><strong>Custo:</strong> 15 IC</p><p><strong>Tipo:</strong> Field</p>"
        }
    }
}
