{
    "name": "Big Tornado",
    "type": "item",
    "img": "modules/omini-system-assets/assets/icons/skills/enemies/marinas/general/io/big_tornado.webp",
    "system": {
        "props": {
            "itemType": "skill",
            "skillType": "Action",
            "rarity": "mythic",
            "tier": 10,
            "source": "Io (Marina)",
            "icCost": 16,
            "damage": "8d8 Wind",
            "actionMacro": "big_tornado_action",
            "description": "<p><strong>[Big Tornado]</strong></p><p>Tornado Gigante combinado.</p><p><strong>Custo:</strong> 16 IC</p><p><strong>Tipo:</strong> Action</p>"
        }
    }
}
