{
    "name": "Fogaréu Eterno",
    "type": "item",
    "img": "modules/omini-system-assets/assets/icons/skills/enemies/folklore/cangaco/mula_sem_cabeça/fogaréu_eterno.webp",
    "system": {
        "props": {
            "itemType": "skill",
            "skillType": "Action",
            "rarity": "epic",
            "tier": 9,
            "source": "Mula Sem Cabeça (Folclore)",
            "icCost": 20,
            "damage": "10d8 Fire",
            "actionMacro": "fogaréu_eterno_action",
            "description": "<p><strong>[Fogaréu Eterno]</strong></p><p>Jato de plasma do pescoço. Dano espiritual.</p><p><strong>Custo:</strong> 20 IC</p><p><strong>Tipo:</strong> Action</p>"
        }
    }
}
